ordeq_pillow/__init__.py
ordeq_pillow/_version.py
ordeq_pillow/image.py
ordeq_pillow/pdf_to_image.py
ordeq_pillow/py.typed
ordeq_pillow-0.1.0.dist-info/licenses/LICENSE
ordeq_pillow-0.1.0.dist-info/METADATA
ordeq_pillow-0.1.0.dist-info/WHEEL
ordeq_pillow-0.1.0.dist-info/top_level.txt
ordeq_pillow-0.1.0.dist-info/RECORD
