Metadata-Version: 2.4
Name: ordeq_pillow
Version: 0.1.0
Author: Niels Neerhoff, Simon Brugman
Maintainer: Niels Neerhoff, Simon Brugman
License-Expression: MIT
Requires-Python: >=3.10
License-File: LICENSE
Requires-Dist: ordeq>=1.0.0
Requires-Dist: pillow
Provides-Extra: pdf
Requires-Dist: pdf2image; extra == "pdf"
Dynamic: license-file
